my_library_mk_005_1/__init__.py
my_library_mk_005_1/input.py
my_library_mk_005_1/my_module.py
my_library_mk_005_1-0.1.dist-info/METADATA
my_library_mk_005_1-0.1.dist-info/WHEEL
my_library_mk_005_1-0.1.dist-info/top_level.txt
my_library_mk_005_1-0.1.dist-info/RECORD
